atlastk/Atlas.py
atlastk/XDHq.py
atlastk/XDHqFaaS.py
atlastk/XDHqFaaS2.py
atlastk/XDHqFaaS3.py
atlastk/XDHqSHRD.py
atlastk/XDHqXML.py
atlastk/__init__.py
atlastk/__main__.py
atlastk/atlastk.py
atlastk-0.13.3.dist-info/LICENSE
atlastk-0.13.3.dist-info/METADATA
atlastk-0.13.3.dist-info/WHEEL
atlastk-0.13.3.dist-info/top_level.txt
atlastk-0.13.3.dist-info/RECORD
