Metadata-Version: 2.1
Name: atlastk
Version: 0.13.3
Summary: World's lightest toolkit to quickly and easily add a GUI to your Python programs and bring them online. 
Home-page: https://atlastk.org
Author: Claude SIMON
License: UNKNOWN
Keywords: GUI,web,Atlas toolkit
Platform: UNKNOWN
Classifier: Environment :: Web Environment
Classifier: Development Status :: 5 - Production/Stable
Classifier: Intended Audience :: Developers
Classifier: Intended Audience :: Education
Classifier: Intended Audience :: Other Audience
Classifier: License :: OSI Approved :: MIT License 
Classifier: Operating System :: OS Independent
Classifier: Programming Language :: Python :: 2
Classifier: Programming Language :: Python :: 3
Classifier: Topic :: Internet :: WWW/HTTP :: Dynamic Content
Classifier: Topic :: Software Development :: User Interfaces
